apitaxcore/__init__.py
apitaxcore/module.py
apitaxcore/builders/BodyBuilder.py
apitaxcore/builders/Builder.py
apitaxcore/builders/CookieBuilder.py
apitaxcore/builders/DictBuilder.py
apitaxcore/builders/HeaderBuilder.py
apitaxcore/builders/ListBuilder.py
apitaxcore/builders/QueryBuilder.py
apitaxcore/builders/__init__.py
apitaxcore/catalog/Catalog.py
apitaxcore/catalog/EndpointCatalog.py
apitaxcore/catalog/__init__.py
apitaxcore/config/Config.py
apitaxcore/config/__init__.py
apitaxcore/drivers/Driver.py
apitaxcore/drivers/DriverFactory.py
apitaxcore/drivers/Drivers.py
apitaxcore/drivers/__init__.py
apitaxcore/drivers/builtin/__init__.py
apitaxcore/flow/LoadedDrivers.py
apitaxcore/flow/__init__.py
apitaxcore/flow/requests/ApitaxRequest.py
apitaxcore/flow/requests/LowLevelRequest.py
apitaxcore/flow/requests/Request.py
apitaxcore/flow/requests/__init__.py
apitaxcore/flow/responses/ApitaxResponse.py
apitaxcore/flow/responses/LowLevelResponse.py
apitaxcore/flow/responses/Response.py
apitaxcore/flow/responses/__init__.py
apitaxcore/logs/BufferedLog.py
apitaxcore/logs/Log.py
apitaxcore/logs/LogDriver.py
apitaxcore/logs/LogSlate.py
apitaxcore/logs/StandardLog.py
apitaxcore/logs/__init__.py
apitaxcore/models/Credentials.py
apitaxcore/models/Options.py
apitaxcore/models/State.py
apitaxcore/models/User.py
apitaxcore/models/__init__.py
apitaxcore/utilities/Arguments.py
apitaxcore/utilities/Async.py
apitaxcore/utilities/Booleans.py
apitaxcore/utilities/Converters.py
apitaxcore/utilities/Files.py
apitaxcore/utilities/Json.py
apitaxcore/utilities/Npm.py
apitaxcore/utilities/Numbers.py
apitaxcore/utilities/Strings.py
apitaxcore/utilities/__init__.py
apitaxcore-3.0.9.dist-info/LICENSE
apitaxcore-3.0.9.dist-info/METADATA
apitaxcore-3.0.9.dist-info/WHEEL
apitaxcore-3.0.9.dist-info/top_level.txt
apitaxcore-3.0.9.dist-info/RECORD
