Metadata-Version: 2.1
Name: apitaxcore
Version: 3.0.9
Summary: Provides utilities and integration code which may be useful when developing various drivers for use within the Apitax framework.
Home-page: https://github.com/ShawnClake/Apitax
Author: Shawn Clake
Author-email: shawn.clake@gmail.com
License: UNKNOWN
Keywords: restful,api,commandtax,scriptax
Platform: UNKNOWN
Classifier: Programming Language :: Python :: 3
Classifier: License :: OSI Approved :: MIT License
Classifier: Operating System :: OS Independent
Requires-Dist: python-dateutil (==2.6.0)
Requires-Dist: typing (==3.5.2.2)
Requires-Dist: xmltodict
Requires-Dist: requests
